[
  {
    "key": "dsports",
    "name": "D Sports",
    "image": "https://upload.wikimedia.org/wikipedia/commons/5/5a/DSports.png",
    "category": "Sports",
    "quality": "HD",
    "status": "live",
    "sort": 0,
    "views": 0,
    "live": 0,
    "resolution": "",
    "play_token": "1781831067.2c3828ab28fb281acd8441e8b232b70bfdce8c02d6f6b4d68b4863be8959e59b",
    "play_exp": 1781831067,
    "source_types": [
      "dash"
    ],
    "source_count": 1
  },
  {
    "key": "golive",
    "name": "GOLIVE - English",
    "image": "https://rtb-images.glueapi.io/320x0/live/GoLiveNew.png",
    "category": "Sports",
    "quality": "HD",
    "status": "live",
    "sort": 1,
    "views": 0,
    "live": 0,
    "resolution": "",
    "play_token": "1781831067.fe9183d896c7e460a40486738600de45e099aeaa34e334fc6f214d6ddbd32b6e",
    "play_exp": 1781831067,
    "source_types": [
      "hls"
    ],
    "source_count": 1
  },
  {
    "key": "ios3",
    "name": "iOS - FIFA 2026 Server 3",
    "image": "https://i.guim.co.uk/img/media/993d3ff63f81efb3bd6d4a93be34a98a815a2453/0_0_5000_3297/master/5000.jpg?width=1900&dpr=2&s=none&crop=none",
    "category": "Sports",
    "quality": "HD",
    "status": "live",
    "sort": 2,
    "views": 0,
    "live": 0,
    "resolution": "",
    "play_token": "1781831067.04885bf6ed6067830f3ba86ee600aa7ebb022828aedf6726ee66a74313cfff01",
    "play_exp": 1781831067,
    "source_types": [
      "hls"
    ],
    "source_count": 1
  },
  {
    "key": "beinsports",
    "name": "iOS - beIN SPORTS 1 (Arabic)",
    "image": "https://i.ibb.co.com/S7tZS6cg/Bein-Sports-1-Direct.png",
    "category": "Sports",
    "quality": "HD",
    "status": "live",
    "sort": 2,
    "views": 0,
    "live": 0,
    "resolution": "",
    "play_token": "1781831067.d166643821ba614de626f9fb6b684019cf6e2636d4f04a923c25c5d5f0edce26",
    "play_exp": 1781831067,
    "source_types": [
      "hls"
    ],
    "source_count": 1
  },
  {
    "key": "cazetv",
    "name": "CazéTV 1080p 60Fps",
    "image": "https://upload.wikimedia.org/wikipedia/en/thumb/6/64/Caz%C3%A9TV_logo.svg/1280px-Caz%C3%A9TV_logo.svg.png",
    "category": "Sports",
    "quality": "HD",
    "status": "live",
    "sort": 4,
    "views": 0,
    "live": 0,
    "resolution": "",
    "play_token": "1781831067.1d82ad19eda9f3f1803bf1abd7208eff9bc9d8be5e6270408109684950deccf7",
    "play_exp": 1781831067,
    "source_types": [
      "dash"
    ],
    "source_count": 1
  },
  {
    "key": "iptv-729668",
    "name": "AR: beIN SPORTS Pop Up FHD",
    "image": "https://raw.githubusercontent.com/tv-logo/tv-logos/main/countries/international/beinsports/old/stacked/bein-sports-int.png",
    "category": "FIFA WC 2026™ beIN MAX Ⓖ",
    "quality": "FHD",
    "status": "live",
    "sort": 7000,
    "views": 0,
    "live": 0,
    "resolution": "",
    "play_token": "1781831067.fc4ddc26d5ededb2a62288eb8fca7e3dc67907b670f1723dc424fd4314781124",
    "play_exp": 1781831067,
    "source_types": [
      "hls",
      "file"
    ],
    "source_count": 5
  },
  {
    "key": "iptv-729021",
    "name": "AR: beIN SPORTS NEWS FHD (H.265)",
    "image": "https://raw.githubusercontent.com/tv-logo/tv-logos/main/countries/international/beinsports/old/stacked/bein-sports-news-arabic-int.png",
    "category": "FIFA WC 2026™ beIN MAX Ⓖ",
    "quality": "FHD",
    "status": "live",
    "sort": 7001,
    "views": 0,
    "live": 0,
    "resolution": "",
    "play_token": "1781831067.8fb80d6142105dace4ec536e4438daf0c4fbf6e0b731e41eb78e0029d41cdec4",
    "play_exp": 1781831067,
    "source_types": [
      "hls",
      "file"
    ],
    "source_count": 5
  },
  {
    "key": "iptv-729022",
    "name": "AR: beIN SPORTS NEWS HD",
    "image": "https://raw.githubusercontent.com/tv-logo/tv-logos/main/countries/international/beinsports/old/stacked/bein-sports-news-arabic-int.png",
    "category": "FIFA WC 2026™ beIN MAX Ⓖ",
    "quality": "HD",
    "status": "live",
    "sort": 7002,
    "views": 0,
    "live": 0,
    "resolution": "",
    "play_token": "1781831067.58614658254d4ed8d6b195a9f328eaef2a1802ecd25bada53db5a6339be89d7c",
    "play_exp": 1781831067,
    "source_types": [
      "hls",
      "file"
    ],
    "source_count": 5
  },
  {
    "key": "iptv-729023",
    "name": "AR: beIN SPORTS FHD (H.265)",
    "image": "https://raw.githubusercontent.com/tv-logo/tv-logos/main/countries/international/beinsports/old/stacked/bein-sports-int.png",
    "category": "FIFA WC 2026™ beIN MAX Ⓖ",
    "quality": "FHD",
    "status": "live",
    "sort": 7003,
    "views": 0,
    "live": 0,
    "resolution": "",
    "play_token": "1781831067.9c37dcda49fe0b72fb520f264b71e0f89eb9d1988f32a1231e1373d6e9a7459d",
    "play_exp": 1781831067,
    "source_types": [
      "hls",
      "file"
    ],
    "source_count": 5
  },
  {
    "key": "iptv-729024",
    "name": "AR: beIN SPORTS HD",
    "image": "https://raw.githubusercontent.com/tv-logo/tv-logos/main/countries/international/beinsports/old/stacked/bein-sports-int.png",
    "category": "FIFA WC 2026™ beIN MAX Ⓖ",
    "quality": "HD",
    "status": "live",
    "sort": 7004,
    "views": 0,
    "live": 0,
    "resolution": "",
    "play_token": "1781831067.3392a176ca034490767a6dc728d2a2b294c6ff3a282e49982420b52dde543728",
    "play_exp": 1781831067,
    "source_types": [
      "hls",
      "file"
    ],
    "source_count": 5
  },
  {
    "key": "iptv-729453",
    "name": "TOD WC 01: Arabic Feed: FIFA World Cup 2026: Argentina vs. Algeria",
    "image": "https://i.imgur.com/rIIIAi2.jpeg",
    "category": "FIFA WC 2026™ beIN MAX Ⓖ",
    "quality": "HD",
    "status": "live",
    "sort": 7005,
    "views": 0,
    "live": 0,
    "resolution": "",
    "play_token": "1781831067.a172fd02e47e8478a9b44b7d88725f4af9c3b976d5aaa0998b141640021b97a2",
    "play_exp": 1781831067,
    "source_types": [
      "hls",
      "file"
    ],
    "source_count": 5
  },
  {
    "key": "iptv-729454",
    "name": "TOD WC 02: Arabic Feed: FIFA World Cup 2026: Argentina vs. Algeria - HD",
    "image": "https://i.imgur.com/rIIIAi2.jpeg",
    "category": "FIFA WC 2026™ beIN MAX Ⓖ",
    "quality": "HD",
    "status": "live",
    "sort": 7006,
    "views": 0,
    "live": 0,
    "resolution": "",
    "play_token": "1781831067.d430456495575e7815a42716b09dddcd7025509ace9747bf62b74ec02b156668",
    "play_exp": 1781831067,
    "source_types": [
      "hls",
      "file"
    ],
    "source_count": 5
  },
  {
    "key": "iptv-729558",
    "name": "TOD WC 03: : كأس العالم: الأرجنتين ضد الجزائر - HDR [EN-AR]",
    "image": "https://i.imgur.com/rIIIAi2.jpeg",
    "category": "FIFA WC 2026™ beIN MAX Ⓖ",
    "quality": "4K",
    "status": "live",
    "sort": 7007,
    "views": 0,
    "live": 0,
    "resolution": "",
    "play_token": "1781831067.dc0a1dedc8f7489df70664f92a7e35937caf05fc8749469373497645704b9d2f",
    "play_exp": 1781831067,
    "source_types": [
      "hls",
      "file"
    ],
    "source_count": 5
  },
  {
    "key": "iptv-729576",
    "name": "TOD WC 04: كأس العالم: السعودية ضد أوروغواي - HD",
    "image": "https://i.imgur.com/rIIIAi2.jpeg",
    "category": "FIFA WC 2026™ beIN MAX Ⓖ",
    "quality": "HD",
    "status": "live",
    "sort": 7008,
    "views": 0,
    "live": 0,
    "resolution": "",
    "play_token": "1781831067.e5c376e360b0480416fa369c69fa6d6814e5af3e7f842fbb29ea6a0a310be8d7",
    "play_exp": 1781831067,
    "source_types": [
      "hls",
      "file"
    ],
    "source_count": 5
  },
  {
    "key": "iptv-729577",
    "name": "TOD WC 05: FIFA World Cup: Saudi Arabia vs Uruguay - ENG",
    "image": "https://i.imgur.com/rIIIAi2.jpeg",
    "category": "FIFA WC 2026™ beIN MAX Ⓖ",
    "quality": "HD",
    "status": "down",
    "sort": 7009,
    "views": 0,
    "live": 0,
    "resolution": "",
    "play_token": "1781831067.eff9259a3c395dbb2fdb6c78183c4bc04a07ccc98538026a1215c2da6ddb4659",
    "play_exp": 1781831067,
    "source_types": [
      "hls",
      "file"
    ],
    "source_count": 5
  },
  {
    "key": "iptv-729429",
    "name": "beIN SPORTS 4K HDR",
    "image": "https://assets.bein.com/mena/sites/4/2026/05/4K-HDR-200x200-1.png",
    "category": "FIFA WC 2026™ beIN MAX Ⓖ",
    "quality": "4K",
    "status": "live",
    "sort": 7010,
    "views": 0,
    "live": 0,
    "resolution": "",
    "play_token": "1781831067.65c9c0b221fe67806488058e5710ab80094405fb3e46ed7dca4d8ce02fd4cccc",
    "play_exp": 1781831067,
    "source_types": [
      "hls",
      "file"
    ],
    "source_count": 5
  },
  {
    "key": "iptv-729578",
    "name": "beIN SPORTS 4K HDR*",
    "image": "https://assets.bein.com/mena/sites/4/2026/05/4K-HDR-200x200-1.png",
    "category": "FIFA WC 2026™ beIN MAX Ⓖ",
    "quality": "4K",
    "status": "live",
    "sort": 7011,
    "views": 0,
    "live": 0,
    "resolution": "",
    "play_token": "1781831067.7f1c5980d91562201a751cf89fa0ec8bbf5c7678f55a44a40cfb86eb5f35ee81",
    "play_exp": 1781831067,
    "source_types": [
      "hls",
      "file"
    ],
    "source_count": 5
  },
  {
    "key": "iptv-727604",
    "name": "beIN SPORTS MAX 1 FHD HEVC Ⓖ",
    "image": "https://assets.bein.com/mena/sites/3/2015/06/beIN_SPORTS_MAX1_DIGITAL_Mono.png",
    "category": "FIFA WC 2026™ beIN MAX Ⓖ",
    "quality": "FHD",
    "status": "live",
    "sort": 7012,
    "views": 0,
    "live": 0,
    "resolution": "",
    "play_token": "1781831067.cbab34647d5f00222d9b33d1c2ec0fa10829c198d951c40afe4d467e49b3c9e4",
    "play_exp": 1781831067,
    "source_types": [
      "hls",
      "file"
    ],
    "source_count": 5
  },
  {
    "key": "iptv-727606",
    "name": "beIN SPORTS MAX 1 FHD Ⓖ",
    "image": "https://assets.bein.com/mena/sites/3/2015/06/beIN_SPORTS_MAX1_DIGITAL_Mono.png",
    "category": "FIFA WC 2026™ beIN MAX Ⓖ",
    "quality": "FHD",
    "status": "live",
    "sort": 7013,
    "views": 0,
    "live": 0,
    "resolution": "",
    "play_token": "1781831067.9f6149b5bf0420b76fb37c2ed7bfb26ee13024981b5bb145be2e4819f25c7f92",
    "play_exp": 1781831067,
    "source_types": [
      "hls",
      "file"
    ],
    "source_count": 5
  },
  {
    "key": "iptv-727607",
    "name": "beIN SPORTS MAX 1 HD Ⓖ",
    "image": "https://assets.bein.com/mena/sites/3/2015/06/beIN_SPORTS_MAX1_DIGITAL_Mono.png",
    "category": "FIFA WC 2026™ beIN MAX Ⓖ",
    "quality": "HD",
    "status": "live",
    "sort": 7014,
    "views": 0,
    "live": 0,
    "resolution": "",
    "play_token": "1781831067.85e0c99386ea2c962c52320453236efdc33e7d8e932035efa859268772ef4511",
    "play_exp": 1781831067,
    "source_types": [
      "hls",
      "file"
    ],
    "source_count": 5
  },
  {
    "key": "iptv-727608",
    "name": "beIN SPORTS MAX 1 SD+ Ⓖ",
    "image": "https://assets.bein.com/mena/sites/3/2015/06/beIN_SPORTS_MAX1_DIGITAL_Mono.png",
    "category": "FIFA WC 2026™ beIN MAX Ⓖ",
    "quality": "SD",
    "status": "live",
    "sort": 7015,
    "views": 0,
    "live": 0,
    "resolution": "",
    "play_token": "1781831067.daf1a07890048fd09967de8d774dd65b07b9712c1d44479bf92cf909c56eab12",
    "play_exp": 1781831067,
    "source_types": [
      "hls",
      "file"
    ],
    "source_count": 5
  },
  {
    "key": "iptv-727605",
    "name": "beIN SPORTS MAX 2 FHD HEVC Ⓖ",
    "image": "https://assets.bein.com/mena/sites/3/2015/06/beIN_SPORTS_MAX2_DIGITAL_Mono.png",
    "category": "FIFA WC 2026™ beIN MAX Ⓖ",
    "quality": "FHD",
    "status": "live",
    "sort": 7016,
    "views": 0,
    "live": 0,
    "resolution": "",
    "play_token": "1781831067.4533a132e3d47727c432d7ea39ff5442af7a3c658d58768d9ab8b67906040ad0",
    "play_exp": 1781831067,
    "source_types": [
      "hls",
      "file"
    ],
    "source_count": 5
  },
  {
    "key": "iptv-727609",
    "name": "beIN SPORTS MAX 2 FHD Ⓖ",
    "image": "https://assets.bein.com/mena/sites/3/2015/06/beIN_SPORTS_MAX2_DIGITAL_Mono.png",
    "category": "FIFA WC 2026™ beIN MAX Ⓖ",
    "quality": "FHD",
    "status": "live",
    "sort": 7017,
    "views": 0,
    "live": 0,
    "resolution": "",
    "play_token": "1781831067.9b6d24ab9a2e44a5e15a275319bac32a60ea6a4cb628649fdb08adae4cf2c590",
    "play_exp": 1781831067,
    "source_types": [
      "hls",
      "file"
    ],
    "source_count": 5
  },
  {
    "key": "iptv-727610",
    "name": "beIN SPORTS MAX 2 HD Ⓖ",
    "image": "https://assets.bein.com/mena/sites/3/2015/06/beIN_SPORTS_MAX2_DIGITAL_Mono.png",
    "category": "FIFA WC 2026™ beIN MAX Ⓖ",
    "quality": "HD",
    "status": "live",
    "sort": 7018,
    "views": 0,
    "live": 0,
    "resolution": "",
    "play_token": "1781831067.c53d0e05e480f09d9c4a24819f08d77848fe10f0691b2423b92b2beca78c4ee6",
    "play_exp": 1781831067,
    "source_types": [
      "hls",
      "file"
    ],
    "source_count": 5
  },
  {
    "key": "iptv-727611",
    "name": "beIN SPORTS MAX 2 SD+ Ⓖ",
    "image": "https://assets.bein.com/mena/sites/3/2015/06/beIN_SPORTS_MAX2_DIGITAL_Mono.png",
    "category": "FIFA WC 2026™ beIN MAX Ⓖ",
    "quality": "SD",
    "status": "live",
    "sort": 7019,
    "views": 0,
    "live": 0,
    "resolution": "",
    "play_token": "1781831067.1381066ea8d36c7d2d7ae8383cac0a4d9bd6f04870adc6c8273ced3d59675555",
    "play_exp": 1781831067,
    "source_types": [
      "hls",
      "file"
    ],
    "source_count": 5
  },
  {
    "key": "iptv-727612",
    "name": "beIN SPORTS MAX 3 FHD HEVC Ⓖ",
    "image": "https://assets.bein.com/mena/sites/3/2015/06/beIN_SPORTS_MAX3_DIGITAL_Mono.png",
    "category": "FIFA WC 2026™ beIN MAX Ⓖ",
    "quality": "FHD",
    "status": "live",
    "sort": 7020,
    "views": 0,
    "live": 0,
    "resolution": "",
    "play_token": "1781831067.d20f4e1df9795a0af91bb2d03e99fd37c9cef5cc92e4a68954cf8e70bb797174",
    "play_exp": 1781831067,
    "source_types": [
      "hls",
      "file"
    ],
    "source_count": 5
  },
  {
    "key": "iptv-727613",
    "name": "beIN SPORTS MAX 3 FHD Ⓖ",
    "image": "https://assets.bein.com/mena/sites/3/2015/06/beIN_SPORTS_MAX3_DIGITAL_Mono.png",
    "category": "FIFA WC 2026™ beIN MAX Ⓖ",
    "quality": "FHD",
    "status": "live",
    "sort": 7021,
    "views": 0,
    "live": 0,
    "resolution": "",
    "play_token": "1781831067.83de03e48f3d06cb5744d3c7af81b5e6975b7159a8defcbb3a277560b7d360b6",
    "play_exp": 1781831067,
    "source_types": [
      "hls",
      "file"
    ],
    "source_count": 5
  },
  {
    "key": "iptv-727614",
    "name": "beIN SPORTS MAX 3 HD Ⓖ",
    "image": "https://assets.bein.com/mena/sites/3/2015/06/beIN_SPORTS_MAX3_DIGITAL_Mono.png",
    "category": "FIFA WC 2026™ beIN MAX Ⓖ",
    "quality": "HD",
    "status": "live",
    "sort": 7022,
    "views": 0,
    "live": 0,
    "resolution": "",
    "play_token": "1781831067.d920fd9fc0879e0c72063b7b05c041ad489143e748aa386b6fae583b3eda3350",
    "play_exp": 1781831067,
    "source_types": [
      "hls",
      "file"
    ],
    "source_count": 5
  },
  {
    "key": "iptv-727615",
    "name": "beIN SPORTS MAX 3 SD+ Ⓖ",
    "image": "https://assets.bein.com/mena/sites/3/2015/06/beIN_SPORTS_MAX3_DIGITAL_Mono.png",
    "category": "FIFA WC 2026™ beIN MAX Ⓖ",
    "quality": "SD",
    "status": "live",
    "sort": 7023,
    "views": 0,
    "live": 0,
    "resolution": "",
    "play_token": "1781831067.93a773c4ddcc8644e8d38a7de0ec226cf4079d1c00acb98c78705be17ff9e5fc",
    "play_exp": 1781831067,
    "source_types": [
      "hls",
      "file"
    ],
    "source_count": 5
  },
  {
    "key": "iptv-727616",
    "name": "beIN SPORTS MAX 4 FHD HEVC Ⓖ",
    "image": "https://assets.bein.com/mena/sites/3/2015/06/beIN_SPORTS_MAX4_DIGITAL_Mono.png",
    "category": "FIFA WC 2026™ beIN MAX Ⓖ",
    "quality": "FHD",
    "status": "live",
    "sort": 7024,
    "views": 0,
    "live": 0,
    "resolution": "",
    "play_token": "1781831067.a988ba01a345f55616f6dc85b29b585a64e6ff88c1105b25d97884ef1aa921a1",
    "play_exp": 1781831067,
    "source_types": [
      "hls",
      "file"
    ],
    "source_count": 5
  },
  {
    "key": "iptv-727617",
    "name": "beIN SPORTS MAX 4 FHD Ⓖ",
    "image": "https://assets.bein.com/mena/sites/3/2015/06/beIN_SPORTS_MAX4_DIGITAL_Mono.png",
    "category": "FIFA WC 2026™ beIN MAX Ⓖ",
    "quality": "FHD",
    "status": "live",
    "sort": 7025,
    "views": 0,
    "live": 0,
    "resolution": "",
    "play_token": "1781831067.b0082f75030bcaea61e4a3948fdebf884d325035c856b8ad38ab7595bfb64795",
    "play_exp": 1781831067,
    "source_types": [
      "hls",
      "file"
    ],
    "source_count": 5
  },
  {
    "key": "iptv-727618",
    "name": "beIN SPORTS MAX 4 HD Ⓖ",
    "image": "https://assets.bein.com/mena/sites/3/2015/06/beIN_SPORTS_MAX4_DIGITAL_Mono.png",
    "category": "FIFA WC 2026™ beIN MAX Ⓖ",
    "quality": "HD",
    "status": "live",
    "sort": 7026,
    "views": 0,
    "live": 0,
    "resolution": "",
    "play_token": "1781831067.5d2f30858552374dfdaf4f9b834ff9df49d2c4fefbddf1c91067f0f39eda3d96",
    "play_exp": 1781831067,
    "source_types": [
      "hls",
      "file"
    ],
    "source_count": 5
  },
  {
    "key": "iptv-727619",
    "name": "beIN SPORTS MAX 4 SD+ Ⓖ",
    "image": "https://assets.bein.com/mena/sites/3/2015/06/beIN_SPORTS_MAX4_DIGITAL_Mono.png",
    "category": "FIFA WC 2026™ beIN MAX Ⓖ",
    "quality": "SD",
    "status": "live",
    "sort": 7027,
    "views": 0,
    "live": 0,
    "resolution": "",
    "play_token": "1781831067.ea21f3404cffef31ca8a74c649706a91d3f0ced9f76dba6b1fb5ae62121315e6",
    "play_exp": 1781831067,
    "source_types": [
      "hls",
      "file"
    ],
    "source_count": 5
  },
  {
    "key": "iptv-729433",
    "name": "beIN SPORTS MAX 1 FHD [♣]",
    "image": "https://assets.bein.com/mena/sites/3/2015/06/beIN_SPORTS_MAX1_DIGITAL_Mono.png",
    "category": "FIFA WC 2026™ beIN MAX Ⓖ",
    "quality": "FHD",
    "status": "live",
    "sort": 7028,
    "views": 0,
    "live": 0,
    "resolution": "",
    "play_token": "1781831067.62f8d4e17da3b32913a7fecee1f5fbe24de4417aa5838a5af71ecc929875e189",
    "play_exp": 1781831067,
    "source_types": [
      "hls",
      "file"
    ],
    "source_count": 5
  },
  {
    "key": "iptv-729432",
    "name": "beIN SPORTS MAX 1 FHD HEVC [♣]",
    "image": "https://assets.bein.com/mena/sites/3/2015/06/beIN_SPORTS_MAX1_DIGITAL_Mono.png",
    "category": "FIFA WC 2026™ beIN MAX Ⓖ",
    "quality": "FHD",
    "status": "live",
    "sort": 7029,
    "views": 0,
    "live": 0,
    "resolution": "",
    "play_token": "1781831067.01f5c0cc9a9722fa761ed399c523bfd5fcce29b914e1ff127154f7d3c19d1f4b",
    "play_exp": 1781831067,
    "source_types": [
      "hls",
      "file"
    ],
    "source_count": 5
  }
]